transactional_sqlalchemy/__init__.py
transactional_sqlalchemy/config.py
transactional_sqlalchemy/domains.py
transactional_sqlalchemy/enums.py
transactional_sqlalchemy/interface.py
transactional_sqlalchemy/decorator/transactional.py
transactional_sqlalchemy/repository/__init__.py
transactional_sqlalchemy/repository/base.py
transactional_sqlalchemy/utils/common.py
transactional_sqlalchemy/utils/structure.py
transactional_sqlalchemy/utils/transaction_util.py
transactional_sqlalchemy/wrapper/async_wrapper.py
transactional_sqlalchemy/wrapper/common.py
transactional_sqlalchemy/wrapper/sync_wrapper.py
transactional_sqlalchemy-0.1.9.dist-info/licenses/LICENSE
transactional_sqlalchemy-0.1.9.dist-info/METADATA
transactional_sqlalchemy-0.1.9.dist-info/WHEEL
transactional_sqlalchemy-0.1.9.dist-info/top_level.txt
transactional_sqlalchemy-0.1.9.dist-info/RECORD
