Metadata-Version: 2.4
Name: transactional-sqlalchemy
Version: 0.1.9
Summary: transactional management using sqlalchemy
Author-email: alban <decade_vesper.8i@icloud.com>
Project-URL: Homepage, https://github.com/AlBaneo93/transactional_sqlalchemy
Project-URL: Bug Reports, https://github.com/AlBaneo93/transactional_sqlalchemy/issues
Keywords: sqlalchemy,transaction,async,database,orm
Classifier: Development Status :: 4 - Beta
Classifier: Intended Audience :: Developers
Classifier: License :: OSI Approved :: Apache Software License
Classifier: Operating System :: OS Independent
Classifier: Programming Language :: Python :: 3
Classifier: Programming Language :: Python :: 3.9
Classifier: Programming Language :: Python :: 3.10
Classifier: Programming Language :: Python :: 3.11
Classifier: Programming Language :: Python :: 3.12
Classifier: Topic :: Database
Classifier: Topic :: Software Development :: Libraries :: Python Modules
Classifier: Framework :: AsyncIO
Requires-Python: >=3.9
License-File: LICENSE
Requires-Dist: setuptools>=76.1.0
Requires-Dist: sqlalchemy[asyncio]>=2.0.0
Requires-Dist: tox>=4.28.4
Requires-Dist: tox-uv>=1.26.2
Requires-Dist: wheel>=0.45.1
Provides-Extra: async
Requires-Dist: sqlalchemy[asyncio]>=2.0.0; extra == "async"
Provides-Extra: dev
Requires-Dist: aiosqlite>=0.21.0; extra == "dev"
Requires-Dist: pre-commit>=4.2.0; extra == "dev"
Provides-Extra: test
Requires-Dist: pytest[asyncio]>=8.3.5; extra == "test"
Requires-Dist: pytest-asyncio>=0.25.3; extra == "test"
Requires-Dist: pytest-cov>=6.2.1; extra == "test"
Requires-Dist: aiosqlite>=0.21.0; extra == "test"
Requires-Dist: pytest[asyncio]>=8.3.5; extra == "test"
Requires-Dist: pytest-asyncio>=0.25.3; extra == "test"
Requires-Dist: pytest-sqlalchemy>=0.2.1; extra == "test"
Requires-Dist: pytest-xdist>=3.8.0; extra == "test"
Requires-Dist: pytest-cov>=6.2.1; extra == "test"
Requires-Dist: pytest-html>=4.1.1; extra == "test"
Provides-Extra: lint
Requires-Dist: ruff>=0.1.0; extra == "lint"
Dynamic: license-file
